lbutils/__init__.py
lbutils/abc.py
lbutils/typing.py
lbutils/drivers/__init__.py
lbutils/drivers/common.py
lbutils/drivers/seven_segment.py
lbutils/drivers/seven_segment_hex.py
lbutils/graphics/__init__.py
lbutils/graphics/canvas.py
lbutils/graphics/colours.py
lbutils/graphics/helpers.py
lbutils/graphics/fonts/__init__.py
lbutils/graphics/fonts/base_font.py
lbutils/graphics/fonts/font06.py
lbutils/graphics/fonts/font08.py
lbutils/graphics/fonts/org_01.py
lbutils/helpers/__init__.py
lbutils/helpers/i2c.py
lbutils/pmods/__init__.py
lbutils/pmods/i2c/__init__.py
lbutils/pmods/spi/__init__.py
lbutils/pmods/spi/oledrgb.py
lbutils_mp-0.2.4.dist-info/LICENCE
lbutils_mp-0.2.4.dist-info/METADATA
lbutils_mp-0.2.4.dist-info/WHEEL
lbutils_mp-0.2.4.dist-info/top_level.txt
lbutils_mp-0.2.4.dist-info/RECORD
