Metadata-Version: 2.1
Name: lbutils-mp
Version: 0.2.4
Summary: Utility library for MicroPython, used at Leeds Beckett University and primarily aimed at the Pico H/W microcontrollers
Author-email: David Love <david.love@leedsbeckett.ac.uk>
Project-URL: Homepage, https://github.com/dlove24/lbutils
Project-URL: Documentation, https://dlove24.github.io/lbutils/lbutils/index.html
Classifier: Programming Language :: Python :: 3
Classifier: License :: OSI Approved :: MIT License
Classifier: Operating System :: OS Independent
Requires-Python: >=3.4
License-File: LICENCE
